scaleway/__init__.py
scaleway/account/__init__.py
scaleway/account/v2/__init__.py
scaleway/account/v2/api.py
scaleway/account/v2/marshalling.py
scaleway/account/v2/types.py
scaleway/account/v3/__init__.py
scaleway/account/v3/api.py
scaleway/account/v3/marshalling.py
scaleway/account/v3/types.py
scaleway/applesilicon/__init__.py
scaleway/applesilicon/v1alpha1/__init__.py
scaleway/applesilicon/v1alpha1/api.py
scaleway/applesilicon/v1alpha1/content.py
scaleway/applesilicon/v1alpha1/marshalling.py
scaleway/applesilicon/v1alpha1/types.py
scaleway/audit_trail/__init__.py
scaleway/audit_trail/v1alpha1/__init__.py
scaleway/audit_trail/v1alpha1/api.py
scaleway/audit_trail/v1alpha1/marshalling.py
scaleway/audit_trail/v1alpha1/types.py
scaleway/autoscaling/__init__.py
scaleway/autoscaling/v1alpha1/__init__.py
scaleway/autoscaling/v1alpha1/api.py
scaleway/autoscaling/v1alpha1/marshalling.py
scaleway/autoscaling/v1alpha1/types.py
scaleway/baremetal/__init__.py
scaleway/baremetal/v1/__init__.py
scaleway/baremetal/v1/api.py
scaleway/baremetal/v1/content.py
scaleway/baremetal/v1/marshalling.py
scaleway/baremetal/v1/types.py
scaleway/baremetal/v3/__init__.py
scaleway/baremetal/v3/api.py
scaleway/baremetal/v3/content.py
scaleway/baremetal/v3/marshalling.py
scaleway/baremetal/v3/types.py
scaleway/billing/__init__.py
scaleway/billing/v2alpha1/__init__.py
scaleway/billing/v2alpha1/api.py
scaleway/billing/v2alpha1/marshalling.py
scaleway/billing/v2alpha1/types.py
scaleway/billing/v2beta1/__init__.py
scaleway/billing/v2beta1/api.py
scaleway/billing/v2beta1/marshalling.py
scaleway/billing/v2beta1/types.py
scaleway/block/__init__.py
scaleway/block/v1/__init__.py
scaleway/block/v1/api.py
scaleway/block/v1/content.py
scaleway/block/v1/marshalling.py
scaleway/block/v1/types.py
scaleway/block/v1alpha1/__init__.py
scaleway/block/v1alpha1/api.py
scaleway/block/v1alpha1/content.py
scaleway/block/v1alpha1/marshalling.py
scaleway/block/v1alpha1/types.py
scaleway/cockpit/__init__.py
scaleway-2.10.2.dist-info/METADATA
scaleway-2.10.2.dist-info/WHEEL
scaleway-2.10.2.dist-info/RECORD
